pyswEOS/H2O.py
pyswEOS/H2ONaCl.py
pyswEOS/NaCl.py
pyswEOS/PhaseDiagramSlice.py
pyswEOS/_H2O.so
pyswEOS/_H2ONaCl.so
pyswEOS/_NaCl.so
pyswEOS/__init__.py
pyswEOS/test_H2O.py
pyswEOS/test_H2ONaCl.py
pyswEOS/test_NaCl.py
pyswEOS-0.2.8.dist-info/METADATA
pyswEOS-0.2.8.dist-info/WHEEL
pyswEOS-0.2.8.dist-info/entry_points.txt
pyswEOS-0.2.8.dist-info/top_level.txt
pyswEOS-0.2.8.dist-info/RECORD
