Metadata-Version: 2.1
Name: pyswEOS
Version: 0.2.8
Summary: Python API of swEOS library which is designed to calculate EOS and thermal dynamic properties of H2O-NaCl system, usually called salt water.
Home-page: https://www.sweos.info
Author: Zhikui Guo
Author-email: zguo@geomar.de
Maintainer: Zhikui Guo
Maintainer-email: zguo@geomar.de
License: UNKNOWN
Keywords: NaCl H2O IAPWS Hydrothermal seawater
Platform: UNKNOWN
Classifier: Intended Audience :: Science/Research
Classifier: Intended Audience :: Developers
Classifier: Intended Audience :: Education
Classifier: Topic :: Scientific/Engineering
Classifier: Topic :: Software Development :: Libraries
Classifier: Programming Language :: Python :: 2.7
Classifier: Programming Language :: Python :: 3.5
Classifier: Programming Language :: Python :: 3.6
Classifier: Programming Language :: Python :: 3.7
Classifier: Programming Language :: Python :: 3.8
Classifier: Programming Language :: Python :: 3.9
Requires-Dist: matplotlib
Requires-Dist: numpy
Requires-Dist: argparse
Requires-Dist: colored
